topsis/__init__.py
topsis/__main__.py
Topsis_Nidhi_101916100-1.0.1.dist-info/LICENSE
Topsis_Nidhi_101916100-1.0.1.dist-info/METADATA
Topsis_Nidhi_101916100-1.0.1.dist-info/WHEEL
Topsis_Nidhi_101916100-1.0.1.dist-info/entry_points.txt
Topsis_Nidhi_101916100-1.0.1.dist-info/top_level.txt
Topsis_Nidhi_101916100-1.0.1.dist-info/RECORD
