Metadata-Version: 2.1
Name: Topsis-Nidhi-101916100
Version: 1.0.1
Summary: TOPSIS method for multiple-criteria decision making (MCDM).
Author: Nidhi Bhasker
Author-email: nidhibhasker001@gmail.com
License: SELF
Platform: UNKNOWN
Classifier: Programming Language :: Python :: 3.9
License-File: LICENSE
Requires-Dist: pandas
Requires-Dist: numpy
